LICENSE
README.md
setup.py
pyqtconfig/__init__.py
pyqtconfig/config.py
pyqtconfig/qt.py
pyqtconfig.egg-info/PKG-INFO
pyqtconfig.egg-info/SOURCES.txt
pyqtconfig.egg-info/dependency_links.txt
pyqtconfig.egg-info/top_level.txt
tests/__init__.py
tests/test_config_dialog.py
tests/test_hooks.py
tests/test_warn_no_appname.py